kawarizmi/__init__.py
kawarizmi/main.py
kawarizmi-1.0.0.dist-info/METADATA
kawarizmi-1.0.0.dist-info/WHEEL
kawarizmi-1.0.0.dist-info/entry_points.txt
kawarizmi-1.0.0.dist-info/top_level.txt
kawarizmi-1.0.0.dist-info/RECORD
